Metadata-Version: 1.0
Name: sshIOS
Version: 1.0.7
Summary: ssh module for Cisco IOS
Home-page: https://github.com/FedericoOlivieri/networkAutomation/blob/master/python/modules/python3/sshIOS/sshIOS/__init__.py
Author: Federico Olivieri
Author-email: lvrfrc87@gmail.com
License: MIT
Platform: UNKNOWN
